{
  "$schema": "https://mintlify.com/schema.json",
  "name": "EKL Observability",
  "logo": {
    "dark": "/logo/locai-light-logo.svg",
    "light": "/logo/locai-logo.svg"
  },
  "favicon": "/favicon.png",
  "colors": {
    "primary": "#0D9373",
    "light": "#07C983",
    "dark": "#0D9373",
    "anchors": {
      "from": "#0D9373",
      "to": "#07C983"
    }
  },
  "theme": "prism",
  "anchors": [
    {
      "name": "Community",
      "icon": "slack",
      "url": "https://locai-workspace.slack.com/archives/C07MX00L8EN"
    }
  ],
  "navigation": [
    {
      "group": "Get Started",
      "pages": [
        "introduction",
        "stack_component",
        "engg_considerations"
      ]
    },
    {
      "group": "Architecture",
      "pages": [
        "architecture/system_architecture",
        "architecture/data_flow_architecture",
        "architecture/ref_system_arch"
      ]
    },
    {
      "group": "Logging",
      "pages": [
        "logging/standard_logging"
      ]
    },
    {
      "group": "Visualization",
      "pages": [
        "visualization/dashboard_visualization",
        "logging/naming_standard"
      ]
    },
    {
      "group": "Extension & Tech Stack",
      "pages": [
        "techstack/introduction"
      ]
    }
  ]
}
